<?xml version="1.0" encoding="UTF-8" ?>
<!DOCTYPE mapper PUBLIC "-//mybatis.org//DTD Mapper 3.0//EN" "http://mybatis.org/dtd/mybatis-3-mapper.dtd" >
<mapper namespace="com.welink.commons.persistence.MessageSummaryDOMapper" >
  <resultMap id="BaseResultMap" type="com.welink.commons.domain.MessageSummaryDO" >
    <!--
      WARNING - @mbggenerated
      This element is automatically generated by MyBatis Generator, do not modify.
      This element was generated on Fri Jun 05 11:51:18 CST 2015.
    -->
    <id column="id" property="id" jdbcType="BIGINT" />
    <result column="profile_id" property="profileId" jdbcType="BIGINT" />
    <result column="building_id" property="buildingId" jdbcType="BIGINT" />
    <result column="community_id" property="communityId" jdbcType="BIGINT" />
    <result column="last_message" property="lastMessage" jdbcType="VARCHAR" />
    <result column="non_read_count" property="nonReadCount" jdbcType="INTEGER" />
    <result column="last_updated" property="lastUpdated" jdbcType="TIMESTAMP" />
    <result column="biz_type" property="bizType" jdbcType="BIGINT" />
    <result column="biz_name" property="bizName" jdbcType="VARCHAR" />
    <result column="date_created" property="dateCreated" jdbcType="TIMESTAMP" />
    <result column="target" property="target" jdbcType="BIGINT" />
    <result column="status" property="status" jdbcType="TINYINT" />
    <result column="messageType" property="messagetype" jdbcType="TINYINT" />
    <result column="msg_type_name" property="msgTypeName" jdbcType="VARCHAR" />
    <result column="content" property="content" jdbcType="VARCHAR" />
  </resultMap>
  <sql id="Example_Where_Clause" >
    <!--
      WARNING - @mbggenerated
      This element is automatically generated by MyBatis Generator, do not modify.
      This element was generated on Fri Jun 05 11:51:18 CST 2015.
    -->
    <where >
      <foreach collection="oredCriteria" item="criteria" separator="or" >
        <if test="criteria.valid" >
          <trim prefix="(" suffix=")" prefixOverrides="and" >
            <foreach collection="criteria.criteria" item="criterion" >
              <choose >
                <when test="criterion.noValue" >
                  and ${criterion.condition}
                </when>
                <when test="criterion.singleValue" >
                  and ${criterion.condition} #{criterion.value}
                </when>
                <when test="criterion.betweenValue" >
                  and ${criterion.condition} #{criterion.value} and #{criterion.secondValue}
                </when>
                <when test="criterion.listValue" >
                  and ${criterion.condition}
                  <foreach collection="criterion.value" item="listItem" open="(" close=")" separator="," >
                    #{listItem}
                  </foreach>
                </when>
              </choose>
            </foreach>
          </trim>
        </if>
      </foreach>
    </where>
  </sql>
  <sql id="Update_By_Example_Where_Clause" >
    <!--
      WARNING - @mbggenerated
      This element is automatically generated by MyBatis Generator, do not modify.
      This element was generated on Fri Jun 05 11:51:18 CST 2015.
    -->
    <where >
      <foreach collection="example.oredCriteria" item="criteria" separator="or" >
        <if test="criteria.valid" >
          <trim prefix="(" suffix=")" prefixOverrides="and" >
            <foreach collection="criteria.criteria" item="criterion" >
              <choose >
                <when test="criterion.noValue" >
                  and ${criterion.condition}
                </when>
                <when test="criterion.singleValue" >
                  and ${criterion.condition} #{criterion.value}
                </when>
                <when test="criterion.betweenValue" >
                  and ${criterion.condition} #{criterion.value} and #{criterion.secondValue}
                </when>
                <when test="criterion.listValue" >
                  and ${criterion.condition}
                  <foreach collection="criterion.value" item="listItem" open="(" close=")" separator="," >
                    #{listItem}
                  </foreach>
                </when>
              </choose>
            </foreach>
          </trim>
        </if>
      </foreach>
    </where>
  </sql>
  <sql id="Base_Column_List" >
    <!--
      WARNING - @mbggenerated
      This element is automatically generated by MyBatis Generator, do not modify.
      This element was generated on Fri Jun 05 11:51:18 CST 2015.
    -->
    id, profile_id, building_id, community_id, last_message, non_read_count, last_updated, 
    biz_type, biz_name, date_created, target, status, messageType, msg_type_name, content
  </sql>
  <select id="selectByExample" resultMap="BaseResultMap" parameterType="com.welink.commons.domain.MessageSummaryDOExample" >
    <!--
      WARNING - @mbggenerated
      This element is automatically generated by MyBatis Generator, do not modify.
      This element was generated on Fri Jun 05 11:51:18 CST 2015.
    -->
    select
    <if test="distinct" >
      distinct
    </if>
    <include refid="Base_Column_List" />
    from message_summary
    <if test="_parameter != null" >
      <include refid="Example_Where_Clause" />
    </if>
    <if test="orderByClause != null" >
      order by ${orderByClause}
    </if>
    <if test="limit != null" >
      limit ${limit}
    </if>
    <if test="offset != null" >
      offset ${offset}
    </if>
  </select>
  <select id="selectByPrimaryKey" resultMap="BaseResultMap" parameterType="java.lang.Long" >
    <!--
      WARNING - @mbggenerated
      This element is automatically generated by MyBatis Generator, do not modify.
      This element was generated on Fri Jun 05 11:51:18 CST 2015.
    -->
    select 
    <include refid="Base_Column_List" />
    from message_summary
    where id = #{id,jdbcType=BIGINT}
  </select>
  <delete id="deleteByPrimaryKey" parameterType="java.lang.Long" >
    <!--
      WARNING - @mbggenerated
      This element is automatically generated by MyBatis Generator, do not modify.
      This element was generated on Fri Jun 05 11:51:18 CST 2015.
    -->
    delete from message_summary
    where id = #{id,jdbcType=BIGINT}
  </delete>
  <delete id="deleteByExample" parameterType="com.welink.commons.domain.MessageSummaryDOExample" >
    <!--
      WARNING - @mbggenerated
      This element is automatically generated by MyBatis Generator, do not modify.
      This element was generated on Fri Jun 05 11:51:18 CST 2015.
    -->
    delete from message_summary
    <if test="_parameter != null" >
      <include refid="Example_Where_Clause" />
    </if>
  </delete>
  <insert id="insert" parameterType="com.welink.commons.domain.MessageSummaryDO" >
    <!--
      WARNING - @mbggenerated
      This element is automatically generated by MyBatis Generator, do not modify.
      This element was generated on Fri Jun 05 11:51:18 CST 2015.
    -->
    <selectKey resultType="java.lang.Long" keyProperty="id" order="AFTER" >
      SELECT LAST_INSERT_ID()
    </selectKey>
    insert into message_summary (profile_id, building_id, community_id, 
      last_message, non_read_count, last_updated, 
      biz_type, biz_name, date_created, 
      target, status, messageType, 
      msg_type_name, content)
    values (#{profileId,jdbcType=BIGINT}, #{buildingId,jdbcType=BIGINT}, #{communityId,jdbcType=BIGINT}, 
      #{lastMessage,jdbcType=VARCHAR}, #{nonReadCount,jdbcType=INTEGER}, #{lastUpdated,jdbcType=TIMESTAMP}, 
      #{bizType,jdbcType=BIGINT}, #{bizName,jdbcType=VARCHAR}, #{dateCreated,jdbcType=TIMESTAMP}, 
      #{target,jdbcType=BIGINT}, #{status,jdbcType=TINYINT}, #{messagetype,jdbcType=TINYINT}, 
      #{msgTypeName,jdbcType=VARCHAR}, #{content,jdbcType=VARCHAR})
  </insert>
  <insert id="insertSelective" parameterType="com.welink.commons.domain.MessageSummaryDO" >
    <!--
      WARNING - @mbggenerated
      This element is automatically generated by MyBatis Generator, do not modify.
      This element was generated on Fri Jun 05 11:51:18 CST 2015.
    -->
    <selectKey resultType="java.lang.Long" keyProperty="id" order="AFTER" >
      SELECT LAST_INSERT_ID()
    </selectKey>
    insert into message_summary
    <trim prefix="(" suffix=")" suffixOverrides="," >
      <if test="profileId != null" >
        profile_id,
      </if>
      <if test="buildingId != null" >
        building_id,
      </if>
      <if test="communityId != null" >
        community_id,
      </if>
      <if test="lastMessage != null" >
        last_message,
      </if>
      <if test="nonReadCount != null" >
        non_read_count,
      </if>
      <if test="lastUpdated != null" >
        last_updated,
      </if>
      <if test="bizType != null" >
        biz_type,
      </if>
      <if test="bizName != null" >
        biz_name,
      </if>
      <if test="dateCreated != null" >
        date_created,
      </if>
      <if test="target != null" >
        target,
      </if>
      <if test="status != null" >
        status,
      </if>
      <if test="messagetype != null" >
        messageType,
      </if>
      <if test="msgTypeName != null" >
        msg_type_name,
      </if>
      <if test="content != null" >
        content,
      </if>
    </trim>
    <trim prefix="values (" suffix=")" suffixOverrides="," >
      <if test="profileId != null" >
        #{profileId,jdbcType=BIGINT},
      </if>
      <if test="buildingId != null" >
        #{buildingId,jdbcType=BIGINT},
      </if>
      <if test="communityId != null" >
        #{communityId,jdbcType=BIGINT},
      </if>
      <if test="lastMessage != null" >
        #{lastMessage,jdbcType=VARCHAR},
      </if>
      <if test="nonReadCount != null" >
        #{nonReadCount,jdbcType=INTEGER},
      </if>
      <if test="lastUpdated != null" >
        #{lastUpdated,jdbcType=TIMESTAMP},
      </if>
      <if test="bizType != null" >
        #{bizType,jdbcType=BIGINT},
      </if>
      <if test="bizName != null" >
        #{bizName,jdbcType=VARCHAR},
      </if>
      <if test="dateCreated != null" >
        #{dateCreated,jdbcType=TIMESTAMP},
      </if>
      <if test="target != null" >
        #{target,jdbcType=BIGINT},
      </if>
      <if test="status != null" >
        #{status,jdbcType=TINYINT},
      </if>
      <if test="messagetype != null" >
        #{messagetype,jdbcType=TINYINT},
      </if>
      <if test="msgTypeName != null" >
        #{msgTypeName,jdbcType=VARCHAR},
      </if>
      <if test="content != null" >
        #{content,jdbcType=VARCHAR},
      </if>
    </trim>
  </insert>
  <select id="countByExample" parameterType="com.welink.commons.domain.MessageSummaryDOExample" resultType="java.lang.Integer" >
    <!--
      WARNING - @mbggenerated
      This element is automatically generated by MyBatis Generator, do not modify.
      This element was generated on Fri Jun 05 11:51:18 CST 2015.
    -->
    select count(*) from message_summary
    <if test="_parameter != null" >
      <include refid="Example_Where_Clause" />
    </if>
  </select>
  <update id="updateByExampleSelective" parameterType="map" >
    <!--
      WARNING - @mbggenerated
      This element is automatically generated by MyBatis Generator, do not modify.
      This element was generated on Fri Jun 05 11:51:18 CST 2015.
    -->
    update message_summary
    <set >
      <if test="record.id != null" >
        id = #{record.id,jdbcType=BIGINT},
      </if>
      <if test="record.profileId != null" >
        profile_id = #{record.profileId,jdbcType=BIGINT},
      </if>
      <if test="record.buildingId != null" >
        building_id = #{record.buildingId,jdbcType=BIGINT},
      </if>
      <if test="record.communityId != null" >
        community_id = #{record.communityId,jdbcType=BIGINT},
      </if>
      <if test="record.lastMessage != null" >
        last_message = #{record.lastMessage,jdbcType=VARCHAR},
      </if>
      <if test="record.nonReadCount != null" >
        non_read_count = #{record.nonReadCount,jdbcType=INTEGER},
      </if>
      <if test="record.lastUpdated != null" >
        last_updated = #{record.lastUpdated,jdbcType=TIMESTAMP},
      </if>
      <if test="record.bizType != null" >
        biz_type = #{record.bizType,jdbcType=BIGINT},
      </if>
      <if test="record.bizName != null" >
        biz_name = #{record.bizName,jdbcType=VARCHAR},
      </if>
      <if test="record.dateCreated != null" >
        date_created = #{record.dateCreated,jdbcType=TIMESTAMP},
      </if>
      <if test="record.target != null" >
        target = #{record.target,jdbcType=BIGINT},
      </if>
      <if test="record.status != null" >
        status = #{record.status,jdbcType=TINYINT},
      </if>
      <if test="record.messagetype != null" >
        messageType = #{record.messagetype,jdbcType=TINYINT},
      </if>
      <if test="record.msgTypeName != null" >
        msg_type_name = #{record.msgTypeName,jdbcType=VARCHAR},
      </if>
      <if test="record.content != null" >
        content = #{record.content,jdbcType=VARCHAR},
      </if>
    </set>
    <if test="_parameter != null" >
      <include refid="Update_By_Example_Where_Clause" />
    </if>
  </update>
  <update id="updateByExample" parameterType="map" >
    <!--
      WARNING - @mbggenerated
      This element is automatically generated by MyBatis Generator, do not modify.
      This element was generated on Fri Jun 05 11:51:18 CST 2015.
    -->
    update message_summary
    set id = #{record.id,jdbcType=BIGINT},
      profile_id = #{record.profileId,jdbcType=BIGINT},
      building_id = #{record.buildingId,jdbcType=BIGINT},
      community_id = #{record.communityId,jdbcType=BIGINT},
      last_message = #{record.lastMessage,jdbcType=VARCHAR},
      non_read_count = #{record.nonReadCount,jdbcType=INTEGER},
      last_updated = #{record.lastUpdated,jdbcType=TIMESTAMP},
      biz_type = #{record.bizType,jdbcType=BIGINT},
      biz_name = #{record.bizName,jdbcType=VARCHAR},
      date_created = #{record.dateCreated,jdbcType=TIMESTAMP},
      target = #{record.target,jdbcType=BIGINT},
      status = #{record.status,jdbcType=TINYINT},
      messageType = #{record.messagetype,jdbcType=TINYINT},
      msg_type_name = #{record.msgTypeName,jdbcType=VARCHAR},
      content = #{record.content,jdbcType=VARCHAR}
    <if test="_parameter != null" >
      <include refid="Update_By_Example_Where_Clause" />
    </if>
  </update>
  <update id="updateByPrimaryKeySelective" parameterType="com.welink.commons.domain.MessageSummaryDO" >
    <!--
      WARNING - @mbggenerated
      This element is automatically generated by MyBatis Generator, do not modify.
      This element was generated on Fri Jun 05 11:51:18 CST 2015.
    -->
    update message_summary
    <set >
      <if test="profileId != null" >
        profile_id = #{profileId,jdbcType=BIGINT},
      </if>
      <if test="buildingId != null" >
        building_id = #{buildingId,jdbcType=BIGINT},
      </if>
      <if test="communityId != null" >
        community_id = #{communityId,jdbcType=BIGINT},
      </if>
      <if test="lastMessage != null" >
        last_message = #{lastMessage,jdbcType=VARCHAR},
      </if>
      <if test="nonReadCount != null" >
        non_read_count = #{nonReadCount,jdbcType=INTEGER},
      </if>
      <if test="lastUpdated != null" >
        last_updated = #{lastUpdated,jdbcType=TIMESTAMP},
      </if>
      <if test="bizType != null" >
        biz_type = #{bizType,jdbcType=BIGINT},
      </if>
      <if test="bizName != null" >
        biz_name = #{bizName,jdbcType=VARCHAR},
      </if>
      <if test="dateCreated != null" >
        date_created = #{dateCreated,jdbcType=TIMESTAMP},
      </if>
      <if test="target != null" >
        target = #{target,jdbcType=BIGINT},
      </if>
      <if test="status != null" >
        status = #{status,jdbcType=TINYINT},
      </if>
      <if test="messagetype != null" >
        messageType = #{messagetype,jdbcType=TINYINT},
      </if>
      <if test="msgTypeName != null" >
        msg_type_name = #{msgTypeName,jdbcType=VARCHAR},
      </if>
      <if test="content != null" >
        content = #{content,jdbcType=VARCHAR},
      </if>
    </set>
    where id = #{id,jdbcType=BIGINT}
  </update>
  <update id="updateByPrimaryKey" parameterType="com.welink.commons.domain.MessageSummaryDO" >
    <!--
      WARNING - @mbggenerated
      This element is automatically generated by MyBatis Generator, do not modify.
      This element was generated on Fri Jun 05 11:51:18 CST 2015.
    -->
    update message_summary
    set profile_id = #{profileId,jdbcType=BIGINT},
      building_id = #{buildingId,jdbcType=BIGINT},
      community_id = #{communityId,jdbcType=BIGINT},
      last_message = #{lastMessage,jdbcType=VARCHAR},
      non_read_count = #{nonReadCount,jdbcType=INTEGER},
      last_updated = #{lastUpdated,jdbcType=TIMESTAMP},
      biz_type = #{bizType,jdbcType=BIGINT},
      biz_name = #{bizName,jdbcType=VARCHAR},
      date_created = #{dateCreated,jdbcType=TIMESTAMP},
      target = #{target,jdbcType=BIGINT},
      status = #{status,jdbcType=TINYINT},
      messageType = #{messagetype,jdbcType=TINYINT},
      msg_type_name = #{msgTypeName,jdbcType=VARCHAR},
      content = #{content,jdbcType=VARCHAR}
    where id = #{id,jdbcType=BIGINT}
  </update>
  <select resultMap="BaseResultMap" parameterType="com.welink.commons.domain.MessageSummaryDOExample" id="selectByExampleWithRowbounds" >
    <!--
      WARNING - @mbggenerated
      This element is automatically generated by MyBatis Generator, do not modify.
      This element was generated on Fri Jun 05 11:51:18 CST 2015.
    -->
    select
    <if test="distinct" >
      distinct
    </if>
    <include refid="Base_Column_List" />
    from message_summary
    <if test="_parameter != null" >
      <include refid="Example_Where_Clause" />
    </if>
    <if test="orderByClause != null" >
      order by ${orderByClause}
    </if>
  </select>
</mapper>